web_files/_WebFile.py
web_files/_WebFrame.py
web_files/_WebMatrix.py
web_files/__init__.py
WebFiles-0.0.1.dist-info/LICENSE
WebFiles-0.0.1.dist-info/METADATA
WebFiles-0.0.1.dist-info/WHEEL
WebFiles-0.0.1.dist-info/top_level.txt
WebFiles-0.0.1.dist-info/RECORD
